code_data_science/__init__.py
code_data_science/data_grid.py
code_data_science/data_table.py
code_data_science/palette.py
code_data_science/scm_link.py
code_data_science/tree_data_grid.py
code_data_science/unique_dictionaries.py
code_data_science/versions.py
code_data_science/clustering_src/constants.py
code_data_science/clustering_src/datasets_loader.py
code_data_science/clustering_src/distributed_utils.py
code_data_science/clustering_src/hf_trainer.py
code_data_science/clustering_src/logging_callback.py
code_data_science/clustering_src/preprocessing_utils.py
code_data_science/clustering_src/training_args.py
code_data_science/clustering_src/utils.py
code_data_science/types/notebook_parameter_types.py
code_data_science/types/py.typed
code_data_science-2.1.2.dist-info/METADATA
code_data_science-2.1.2.dist-info/WHEEL
code_data_science-2.1.2.dist-info/top_level.txt
code_data_science-2.1.2.dist-info/RECORD
