Metadata-Version: 2.1
Name: code_data_science
Version: 2.1.2
Summary: A python implementation of various tools used in code data science.
Author-email: Jonathan Schneider <jonathan@moderne.io>, Kyle Scully <kyle@moderne.io>
License: Apache-2.0
Project-URL: Homepage, https://github.com/moderneinc/code-data-science
Requires-Dist: pandas ==2.0.3
Requires-Dist: ipython ==8.13.0
